Metadata-Version: 2.1
Name: langtranslator
Version: 1.0.4
Summary: Translate your program to different languages.
Home-page: UNKNOWN
Author: Patrik Ackermann
Author-email: patrik_ackermann@outlook.com
License: MIT
Keywords: translate program translation localize localization language languages
Platform: UNKNOWN
